LICENSE
MANIFEST.in
setup.py
bin/s2
bin/s2.py
simplystatic/__init__.py
simplystatic/mdx_mathjax.py
simplystatic/s2page.py
simplystatic/s2site.py
simplystatic/util.py
simplystatic.egg-info/PKG-INFO
simplystatic.egg-info/SOURCES.txt
simplystatic.egg-info/dependency_links.txt
simplystatic.egg-info/requires.txt
simplystatic.egg-info/top_level.txt
simplystatic/data/common/favicon.ico
simplystatic/data/common/s2.ico
simplystatic/data/common/s2.png
simplystatic/data/common/font-awesome/css/font-awesome-ie7.css
simplystatic/data/common/font-awesome/css/font-awesome-ie7.min.css
simplystatic/data/common/font-awesome/css/font-awesome.css
simplystatic/data/common/font-awesome/css/font-awesome.min.css
simplystatic/data/common/font-awesome/font/FontAwesome.otf
simplystatic/data/common/font-awesome/font/fontawesome-webfont.eot
simplystatic/data/common/font-awesome/font/fontawesome-webfont.svg
simplystatic/data/common/font-awesome/font/fontawesome-webfont.ttf
simplystatic/data/common/font-awesome/font/fontawesome-webfont.woff
simplystatic/data/common/font-awesome/less/bootstrap.less
simplystatic/data/common/font-awesome/less/core.less
simplystatic/data/common/font-awesome/less/extras.less
simplystatic/data/common/font-awesome/less/font-awesome-ie7.less
simplystatic/data/common/font-awesome/less/font-awesome.less
simplystatic/data/common/font-awesome/less/icons.less
simplystatic/data/common/font-awesome/less/mixins.less
simplystatic/data/common/font-awesome/less/path.less
simplystatic/data/common/font-awesome/less/variables.less
simplystatic/data/common/font-awesome/scss/_bootstrap.scss
simplystatic/data/common/font-awesome/scss/_core.scss
simplystatic/data/common/font-awesome/scss/_extras.scss
simplystatic/data/common/font-awesome/scss/_icons.scss
simplystatic/data/common/font-awesome/scss/_mixins.scss
simplystatic/data/common/font-awesome/scss/_path.scss
simplystatic/data/common/font-awesome/scss/_variables.scss
simplystatic/data/common/font-awesome/scss/font-awesome-ie7.scss
simplystatic/data/common/font-awesome/scss/font-awesome.scss
simplystatic/data/themes/blog1/chronological_plain_front.tpl
simplystatic/data/themes/blog1/header1.jpg
