Metadata-Version: 1.1
Name: simplystatic
Version: 0.1.0
Summary: A static website generator written in Python.
Home-page: s2.jpablo128.com
Author: jPablo Caballero (jpablo128)
Author-email: jpablo@jpablo128.com
License: UNKNOWN
Download-URL: s2.jpablo128.com/download
Platform: UNKNOWN
